Workbook

Sheet Assumptions
A1: Picacho — pricing & unit economics model
A2: Built 2026-08-10. BLUE cells are inputs you can change; black cells are formulas.
A3: Every downstream sheet references these cells — change one here and the whole model updates.
A5: Provider costs
A6: Kling 1.6 standard — $/second (in code today) | B6: 0.056 | C6: src/lib/generations/providers/video-models.ts. NOTE: fal.ai's live pricing page (fetched 2026-08-10) no longer lists Kling 1.6 at all — treat as deprecated.
A7: Kling 2.5 Turbo Pro — $/second (current fal.ai list) | B7: 0.07 | C7: Source: fal.ai/pricing, fetched 2026-08-10. Closest current-generation replacement for Kling 1.6.
A8: Veo 3 — $/second | B8: 0.4 | C8: Source: fal.ai/pricing, fetched 2026-08-10. Matches the figure already in video-models.ts.
A9: Seconds per 1 credit (Kling baseline) | B9: 5 | C9: 1 credit = one 5-second Kling generation, per the credit peg in video-models.ts.
A10: GPT Image — $/image (high quality, 1024x1024) | B10: 0.167 | C10: Web search 2026-08-10. Medium quality is ~$0.042. Which tier applies depends on OpenAI's default for gpt-image-2.
A11: Claude draft + OpenAI review — $ per attempt | B11: 0.02 | C11: ESTIMATE — not verified. Two short LLM calls per attempt. Replace with real figures from your OpenAI/Anthropic usage dashboards.
A12: Measured from your own database (2026-08-04 to 08-10, n=31)
A13: Average provider attempts per generation | B13: 1.57 | C13: Measured: 47 attempts across 30 completed generations. Each attempt re-runs the paid generation step.
A14: Overall failure rate | B14: 0.267 | C14: Measured: 8 of 30 completed generations failed. Failures burn all 3 attempts AND still charge the user a credit.
A15: Image-only failure rate | B15: 0.5 | C15: Measured: 6 of 12 image generations failed. This is the single biggest cost multiplier in the model.
A16: Commercial
A17: USD per 1 EUR | B17: 1.08 | C17: Set this to your actual Stripe settlement rate.
A18: Stripe fee — % of charge | B18: 0.015 | C18: ESTIMATE for EEA cards on a Spanish account. UK/non-EEA cards are materially higher (~2.5-3.25%). VERIFY in your Stripe dashboard.
A19: Stripe fee — fixed per charge (EUR) | B19: 0.25 | C19: ESTIMATE. VERIFY in your Stripe dashboard.
A20: VAT rate applied | B20: 0.21 | C20: Spain standard rate. For EU B2C digital services you owe the CUSTOMER's country rate (17%-27%) via OSS.
A21: Are listed prices VAT-INCLUSIVE? (1=yes, 0=no) | B21: 1 | C21: CRITICAL. 1 = the VAT comes out of your EUR19. 0 = VAT is added on top at checkout and costs you nothing. Check Stripe Tax settings.
A22: Allowance utilisation (share of credits actually used) | B22: 0.7 | C22: Key lever. 1.00 = every subscriber burns their full monthly allowance.

Sheet Unit economics
A1: Per-subscriber monthly economics (EUR)
A2: Assumes the listed EUR price. Costs are converted from USD at the rate on Assumptions.
A4: Line | B4: Starter | C4: Growth | D4: Studio | E4: Elite | F4: Notes
A5: List price (EUR / month) | B5: 19 | C5: 79 | D5: 299 | E5: 499 | F5: Source: src/lib/pricing.ts (USD) and PLAN_PRICE_IDS_EUR (same numbers in EUR).
A6: Included credits / month | B6: 10 | C6: 40 | D6: 150 | E6: 300 | F6: Source: PLAN_LIMITS in src/lib/plans.ts.
A7: VAT borne by us (if inclusive) | B7: =-B5*Assumptions!$B$21*(Assumptions!$B$20/(1+Assumptions!$B$20)) -> -3.2975207 | C7: =-C5*Assumptions!$B$21*(Assumptions!$B$20/(1+Assumptions!$B$20)) -> -13.710744 | D7: =-D5*Assumptions!$B$21*(Assumptions!$B$20/(1+Assumptions!$B$20)) -> -51.892562 | E7: =-E5*Assumptions!$B$21*(Assumptions!$B$20/(1+Assumptions!$B$20)) -> -86.603306 | F7: If prices are VAT-inclusive this is a real deduction. Flip the switch on Assumptions to see the other case.
A8: Stripe fee | B8: =-(B5*Assumptions!$B$18+Assumptions!$B$19) -> -0.535 | C8: =-(C5*Assumptions!$B$18+Assumptions!$B$19) -> -1.435 | D8: =-(D5*Assumptions!$B$18+Assumptions!$B$19) -> -4.735 | E8: =-(E5*Assumptions!$B$18+Assumptions!$B$19) -> -7.735 | F8: Percentage plus fixed, per successful charge.
A9: Net revenue | B9: =B5+B7+B8 -> 15.167479 | C9: =C5+C7+C8 -> 63.854256 | D9: =D5+D7+D8 -> 242.37244 | E9: =E5+E7+E8 -> 404.66169
A10: Credits actually used | B10: =B6*Assumptions!$B$22 -> 7 | C10: =C6*Assumptions!$B$22 -> 28 | D10: =D6*Assumptions!$B$22 -> 105 | E10: =E6*Assumptions!$B$22 -> 210 | F10: Utilisation lever on Assumptions.
A11: Provider cost per credit (USD) | B11: =(Assumptions!$B$6*Assumptions!$B$9+Assumptions!$B$11)*Assumptions!$B$13 -> 0.471 | C11: =(Assumptions!$B$6*Assumptions!$B$9+Assumptions!$B$11)*Assumptions!$B$13 -> 0.471 | D11: =(Assumptions!$B$6*Assumptions!$B$9+Assumptions!$B$11)*Assumptions!$B$13 -> 0.471 | E11: =(Assumptions!$B$6*Assumptions!$B$9+Assumptions!$B$11)*Assumptions!$B$13 -> 0.471 | F11: One credit = 5s of Kling, plus the draft/review calls, multiplied by the MEASURED average attempts.
A12: Generation cost (EUR) | B12: =-B10*B11/Assumptions!$B$17 -> -3.0527778 | C12: =-C10*C11/Assumptions!$B$17 -> -12.211111 | D12: =-D10*D11/Assumptions!$B$17 -> -45.791667 | E12: =-E10*E11/Assumptions!$B$17 -> -91.583333
A13: Gross margin (EUR) | B13: =B9+B12 -> 12.114702 | C13: =C9+C12 -> 51.643145 | D13: =D9+D12 -> 196.58077 | E13: =E9+E12 -> 313.07836
A14: Gross margin % | B14: =IFERROR(B13/B5,0) -> 0.63761587 | C14: =IFERROR(C13/C5,0) -> 0.6537107 | D14: =IFERROR(D13/D5,0) -> 0.65746077 | E14: =IFERROR(E13/E5,0) -> 0.62741154
A15: Break-even: credits before margin = 0 | B15: =IFERROR(B9/(B11/Assumptions!$B$17),0) -> 34.778934 | C15: =IFERROR(C9/(C11/Assumptions!$B$17),0) -> 146.4174 | D15: =IFERROR(D9/(D11/Assumptions!$B$17),0) -> 555.75846 | E15: =IFERROR(E9/(E11/Assumptions!$B$17),0) -> 927.88669 | F15: How many credits a subscriber can burn before that subscription stops making money.
A16: Headroom vs included allowance | B16: =IFERROR(B15/B6,0) -> 3.4778934 | C16: =IFERROR(C15/C6,0) -> 3.6604351 | D16: =IFERROR(D15/D6,0) -> 3.7050564 | E16: =IFERROR(E15/E6,0) -> 3.0929556 | F16: Under 100% means a subscriber who uses their FULL allowance loses you money.
A18: Revenue per credit (EUR) | B18: =B9/B6 -> 1.5167479 | C18: =C9/C6 -> 1.5963564 | D18: =D9/D6 -> 1.6158163 | E18: =E9/E6 -> 1.3488723 | F18: Elite is the weakest of the four on this line — it sells credits cheaper than Studio while attracting the heaviest users.
A19: Cost per credit (EUR) | B19: =B11/Assumptions!$B$17 -> 0.43611111 | C19: =C11/Assumptions!$B$17 -> 0.43611111 | D19: =D11/Assumptions!$B$17 -> 0.43611111 | E19: =E11/Assumptions!$B$17 -> 0.43611111
A20: Markup | B20: =IFERROR(B18/B19,0) -> 3.4778934 | C20: =IFERROR(C18/C19,0) -> 3.6604351 | D20: =IFERROR(D18/D19,0) -> 3.7050564 | E20: =IFERROR(E18/E19,0) -> 3.0929556

Sheet Money leaks
A1: Uncapped or mispriced cost paths
A2: Each of these spends provider money WITHOUT consuming a plan credit, or spends more than the credit charged. Ordered by severity.
A4: Leak | B4: Severity | C4: Units/mo | D4: Cost (EUR) | E4: What's happening, and the fix
A5: Unlimited AI character photos | B5: CRITICAL | C5: 50 | D5: =-C5*Assumptions!$B$10/Assumptions!$B$17 -> -7.7314815 | E5: generateReferenceImage in src/lib/characters/actions.ts meters only plan='none' accounts (2 lifetime). Every PAYING plan gets unlimited AI-generated reference photos that cost real money and consume ZERO credits. A Starter subscriber on EUR19 generating 50 photos/month costs more than they pay. Fix: charge a credit (or a fraction) per generated reference photo, or cap per plan.
A6: Failed generations bill 3x | B6: HIGH | C6: 8 | D6: =-C6*(Assumptions!$B$6*Assumptions!$B$9+Assumptions!$B$11)*3/Assumptions!$B$17 -> -6.6666667 | E6: Measured 26.7% failure rate; every failure burns all 3 attempts. You pay 3 provider calls and collect 1 credit, and the user gets nothing — so they are also likely to retry, doubling it again. Fix: stop charging a credit for a total failure, and cut max attempts to 2 for image generations, where the observed failure rate is 50%.
A7: Dialogue / lipsync not metered | B7: MEDIUM | C7: 20 | D7: =-C7*0.3/Assumptions!$B$17 -> -5.5555556 | E7: wantsDialogue adds ElevenLabs speech plus a Sync Labs lipsync re-render, but creditWeight is unchanged (src/lib/generations/actions.ts). A dialogue video costs materially more than a silent one and is charged identically. Cost per unit is an ESTIMATE. Fix: add a credit surcharge when dialogue is present.
A8: Voice mode is unmetered | B8: MEDIUM | C8: 100 | D8: =-C8*0.02/Assumptions!$B$17 -> -1.8518519 | E8: Voice mode calls OpenAI Whisper for every utterance and OpenAI TTS for every agent reply, with no cap and no credit cost. The new conversational agent speaks 3-4 lines per generation, multiplying this. Cost per exchange is an ESTIMATE. Fix: cap sessions per day, or fold voice into the credit system.
A9: Stopped generations still billed | B9: LOW | C9: 2 | D9: =-C9*(Assumptions!$B$6*Assumptions!$B$9+Assumptions!$B$11)/Assumptions!$B$17 -> -0.55555556 | E9: Cancellation is cooperative, so a provider call already in flight completes and is billed even though the result is discarded. Largely unavoidable without provider-side abort support. Already documented in discardStoppedGeneration.
A10: Total leak per active subscriber / month | D10: =SUM(D5:D9) -> -22.361111 | E10: Compare against Starter net revenue on 'Unit economics' row 9. Units/mo are illustrative — change the blue cells to your own expectation.

Sheet Competitors
A1: Competitor pricing (researched 2026-08-10)
A2: Entry price is the cheapest paid tier. Direct comparison is imperfect: these tools meter differently (per credit, per minute, per seat).
A4: Product | B4: Entry / mo | C4: Top public tier | D4: Model | E4: Position vs Picacho
A5: Picacho | B5: $19 | C5: $499 (Elite) | D5: Credits (1 = 5s video) | E5: Highest top-end price of any product listed here.
A6: HeyGen | B6: $29 (Creator) | C6: $149 (Business) | D6: Credits per minute | E6: Avatar-led marketing video. Its TOP public tier is under a third of Picacho Elite.
A7: Synthesia | B7: $22 (Starter) | C7: Enterprise (quoted) | D7: Credits / minutes | E7: Avatar video for training and comms. Closest analogue to the Starter tier.
A8: Runway | B8: $15 (Standard) | C8: Enterprise (quoted) | D8: Credits / minutes | E8: Cinematic generative video. Cheapest entry point of the group.
A9: Kling AI (direct) | B9: $6.99 | C9: $180 | D9: Credits | E9: The same underlying model Picacho resells, bought direct. This is the price anchor customers will find.
A11: Reading of the comparison
A12: • Starter at $19 for 10 generations is $1.90 per generation. A customer can buy Kling directly for $6.99/mo. The pipeline (draft, review, validate, character consistency) has to be worth that gap, and the pricing page currently does not argue for it.
A13: • Studio ($299) and Elite ($499) sit far above every public competitor tier found. HeyGen's top public tier is $149. Unless Elite is being sold to agencies with a named outcome attached, those two tiers will struggle on a comparison page.
A14: • Every competitor above offers a free tier or trial. Picacho's plan='none' gives 2 AI reference photos and zero generations, so a prospect cannot experience the core product before paying.
A15: • Elite sells credits cheaper than Studio ($1.66 vs $1.99 per credit) while attracting the heaviest users — the discount runs the wrong way relative to usage risk.
A17: Sources: fal.ai/pricing (fetched 2026-08-10); vendor pricing pages and comparison roundups via web search 2026-08-10. Competitor tiers change often — re-check before publishing any comparison.
